plovary.py
plovary-0.2.4.dist-info/LICENSE
plovary-0.2.4.dist-info/METADATA
plovary-0.2.4.dist-info/WHEEL
plovary-0.2.4.dist-info/top_level.txt
plovary-0.2.4.dist-info/zip-safe
plovary-0.2.4.dist-info/RECORD
