Metadata-Version: 2.1
Name: plovary
Version: 0.2.4
Summary: Plover dictionary generation library
Home-page: https://github.com/42triangles/plovary
Author: 42triangles
Author-email: 42triangles@tutanota.com
License: Unlicense
Keywords: plover,plover_plugin
Platform: UNKNOWN
